langextract_vllm/__init__.py
langextract_vllm/provider.py
langextract_vllm-0.2.0.dist-info/METADATA
langextract_vllm-0.2.0.dist-info/WHEEL
langextract_vllm-0.2.0.dist-info/entry_points.txt
langextract_vllm-0.2.0.dist-info/licenses/LICENSE
langextract_vllm-0.2.0.dist-info/RECORD
