Metadata-Version: 2.4
Name: langextract-vllm
Version: 0.2.0
Summary: LangExtract provider plugin for VLLM
Project-URL: Homepage, https://github.com/langextract/langextract-vllm
Project-URL: Repository, https://github.com/langextract/langextract-vllm
Project-URL: Documentation, https://langextract-vllm.readthedocs.io
Project-URL: Bug Tracker, https://github.com/langextract/langextract-vllm/issues
Project-URL: Changelog, https://github.com/langextract/langextract-vllm/blob/main/CHANGELOG.md
Author-email: wuli666 <421774554@qq.com>
Maintainer-email: LangExtract Team <contact@langextract.dev>
License-Expression: Apache-2.0
License-File: LICENSE
Keywords: extraction,gpu,inference,langextract,llm,nlp,pytorch,vllm
Classifier: Development Status :: 4 - Beta
Classifier: Intended Audience :: Developers
Classifier: Intended Audience :: Science/Research
Classifier: License :: OSI Approved :: Apache Software License
Classifier: Operating System :: OS Independent
Classifier: Programming Language :: Python :: 3
Classifier: Programming Language :: Python :: 3.10
Classifier: Programming Language :: Python :: 3.11
Classifier: Programming Language :: Python :: 3.12
Classifier: Topic :: Scientific/Engineering :: Artificial Intelligence
Classifier: Topic :: Software Development :: Libraries :: Python Modules
Classifier: Topic :: Text Processing :: Linguistic
Requires-Python: >=3.10
Requires-Dist: langextract>=1.0.0
Requires-Dist: transformers>=4.30.0
Requires-Dist: vllm>=0.5.0
Provides-Extra: dev
Requires-Dist: black>=23.0.0; extra == 'dev'
Requires-Dist: flake8>=6.0.0; extra == 'dev'
Requires-Dist: isort>=5.12.0; extra == 'dev'
Requires-Dist: mypy>=1.0.0; extra == 'dev'
Requires-Dist: pytest-cov>=4.0.0; extra == 'dev'
Requires-Dist: pytest>=7.0.0; extra == 'dev'
Provides-Extra: docs
Requires-Dist: myst-parser>=1.0.0; extra == 'docs'
Requires-Dist: sphinx-rtd-theme>=1.2.0; extra == 'docs'
Requires-Dist: sphinx>=5.0.0; extra == 'docs'
Provides-Extra: test
Requires-Dist: pytest-cov>=4.0.0; extra == 'test'
Requires-Dist: pytest-mock>=3.10.0; extra == 'test'
Requires-Dist: pytest>=7.0.0; extra == 'test'
